d2c/__init__.py
d2c-0.0.0.dist-info/LICENSE
d2c-0.0.0.dist-info/WHEEL
d2c-0.0.0.dist-info/METADATA
d2c-0.0.0.dist-info/RECORD
